LICENSE
MANIFEST.in
README.md
requirements.txt
setup.cfg
setup.py
versioneer.py
./.travis.yml
./readthedocs.yml
./docs/environment.yml
intake_accumulo/__init__.py
intake_accumulo/_version.py
intake_accumulo/source.py
intake_accumulo.egg-info/PKG-INFO
intake_accumulo.egg-info/SOURCES.txt
intake_accumulo.egg-info/dependency_links.txt
intake_accumulo.egg-info/not-zip-safe
intake_accumulo.egg-info/pbr.json
intake_accumulo.egg-info/requires.txt
intake_accumulo.egg-info/top_level.txt
intake_accumulo/accumulo/__init__.py
intake_accumulo/accumulo/proxy/AccumuloProxy.py
intake_accumulo/accumulo/proxy/__init__.py
intake_accumulo/accumulo/proxy/constants.py
intake_accumulo/accumulo/proxy/ttypes.py
tests/__init__.py
tests/test_intake_accumulo.py
tests/utils.py