Metadata-Version: 1.2
Name: intake-accumulo
Version: 0.1.1
Summary: Intake Accumulo plugin
Home-page: https://github.com/ContinuumIO/intake-accumulo
Maintainer: Joseph Crail
Maintainer-email: jbcrail@gmail.com
License: BSD
Platform: UNKNOWN
